alguns/__init__.py
alguns/alguns.py
alguns/custom_errors.py
alguns/symbols.py
LICENSE
README.md
alguns-0.1.6.dist-info/LICENSE
alguns-0.1.6.dist-info/WHEEL
alguns-0.1.6.dist-info/METADATA
alguns-0.1.6.dist-info/RECORD
