Metadata-Version: 2.1
Name: alguns
Version: 0.1.6
Summary: A crypto library for encrypting text data.
Home-page: https://github.com/dotX12/AlgunsCrypt
License: Apache Software License, BSD License (BSD or Apache License, Version 2.0)
Keywords: crypto,alguns,python,PKCS7,AES,base64,symmetric,decrypt,encrypt
Author: dotX12
Requires-Python: >=3,<4
Classifier: License :: Other/Proprietary License
Classifier: Programming Language :: Python :: 3
Classifier: Programming Language :: Python :: 3.4
Classifier: Programming Language :: Python :: 3.5
Classifier: Programming Language :: Python :: 3.6
Classifier: Programming Language :: Python :: 3.7
Classifier: Programming Language :: Python :: 3.8
Classifier: Programming Language :: Python :: 3.9
Requires-Dist: cffi (==1.14.5)
Requires-Dist: cryptography (==3.4.7)
Requires-Dist: pycparser (==2.20)
Requires-Dist: six (>=1.16.0,<2.0.0)
Project-URL: Repository, https://github.com/dotX12/AlgunsCrypt
